test.py
rf95modem/__init__.py
rf95modem/reader.py
rf95modem-0.2.0.dist-info/LICENSE
rf95modem-0.2.0.dist-info/METADATA
rf95modem-0.2.0.dist-info/WHEEL
rf95modem-0.2.0.dist-info/top_level.txt
rf95modem-0.2.0.dist-info/RECORD
