Metadata-Version: 2.1
Name: rf95modem
Version: 0.2.0
Summary: Python library to send and receive data over LoRa via a rf95modem
Author-email: Alvar Penning <post@0x21.biz>
Project-URL: Homepage, https://github.com/oxzi/rf95modem-py
Project-URL: Bug Tracker, https://github.com/oxzi/rf95modem-py/issues
Classifier: Development Status :: 3 - Alpha
Classifier: License :: OSI Approved :: ISC License (ISCL)
Classifier: Operating System :: OS Independent
Classifier: Programming Language :: Python :: 3
Classifier: Topic :: Terminals :: Serial
Requires-Python: >=3.7
License-File: LICENSE
Requires-Dist: pyserial ==3.5
